{
  "providers": {
    "awscloudformation": {
      "AuthRoleName": "amplify-cherrye-dev-113949-authRole",
      "UnauthRoleArn": "arn:aws:iam::431435831859:role/amplify-cherrye-dev-113949-unauthRole",
      "AuthRoleArn": "arn:aws:iam::431435831859:role/amplify-cherrye-dev-113949-authRole",
      "Region": "us-west-2",
      "DeploymentBucketName": "amplify-cherrye-dev-113949-deployment",
      "UnauthRoleName": "amplify-cherrye-dev-113949-unauthRole",
      "StackName": "amplify-cherrye-dev-113949",
      "StackId": "arn:aws:cloudformation:us-west-2:431435831859:stack/amplify-cherrye-dev-113949/26c1ca30-a959-11eb-ba18-0623b08d5ae3",
      "AmplifyAppId": "d2kp37kexnw07w"
    }
  },
  "function": {
    "cakeFunction": {
      "build": true,
      "providerPlugin": "awscloudformation",
      "service": "Lambda",
      "lastBuildTimeStamp": "2021-04-30T02:27:59.317Z",
      "lastPackageTimeStamp": "2021-04-30T02:28:00.126Z",
      "distZipFilename": "cakeFunction-47704f5851463741537a-build.zip",
      "s3Bucket": {
        "deploymentBucketName": "amplify-cherrye-dev-113949-deployment",
        "s3Key": "amplify-builds/cakeFunction-47704f5851463741537a-build.zip"
      },
      "providerMetadata": {
        "s3TemplateURL": "https://s3.amazonaws.com/amplify-cherrye-dev-113949-deployment/amplify-cfn-templates/function/cakeFunction-cloudformation-template.json",
        "logicalId": "functioncakeFunction"
      },
      "lastPushTimeStamp": "2021-04-30T05:32:02.576Z",
      "output": {
        "Region": "us-west-2",
        "Arn": "arn:aws:lambda:us-west-2:431435831859:function:cakeFunction-dev",
        "Name": "cakeFunction-dev",
        "LambdaExecutionRole": "cherryeLambdaRole1333e991-dev"
      },
      "lastPushDirHash": "1jly6eP/emW29a9APPRxL34xt2c="
    },
    "handlecartitemsFunction": {
      "build": true,
      "providerPlugin": "awscloudformation",
      "service": "Lambda",
      "dependsOn": [
        {
          "category": "function",
          "resourceName": "cakeFunction",
          "attributes": [
            "Name"
          ]
        },
        {
          "category": "api",
          "resourceName": "cherryeAPI",
          "attributes": [
            "ApiName",
            "ApiId"
          ]
        }
      ],
      "lastBuildTimeStamp": "2021-04-30T05:29:44.729Z",
      "lastPackageTimeStamp": "2021-04-30T05:29:45.610Z",
      "distZipFilename": "handlecartitemsFunction-504e5249566d67636857-build.zip",
      "s3Bucket": {
        "deploymentBucketName": "amplify-cherrye-dev-113949-deployment",
        "s3Key": "amplify-builds/handlecartitemsFunction-504e5249566d67636857-build.zip"
      },
      "providerMetadata": {
        "s3TemplateURL": "https://s3.amazonaws.com/amplify-cherrye-dev-113949-deployment/amplify-cfn-templates/function/handlecartitemsFunction-cloudformation-template.json",
        "logicalId": "functionhandlecartitemsFunction"
      },
      "lastPushTimeStamp": "2021-04-30T05:32:02.626Z",
      "output": {
        "Region": "us-west-2",
        "Arn": "arn:aws:lambda:us-west-2:431435831859:function:handlecartitemsFunction-dev",
        "Name": "handlecartitemsFunction-dev",
        "LambdaExecutionRole": "cherryeLambdaRoled21a9f9f-dev"
      },
      "lastPushDirHash": "YPl45KIN6xVeJBKsC8SqOnVAXUQ="
    }
  },
  "api": {
    "cherryeAPI": {
      "service": "API Gateway",
      "providerPlugin": "awscloudformation",
      "dependsOn": [
        {
          "category": "function",
          "resourceName": "cakeFunction",
          "attributes": [
            "Name",
            "Arn"
          ]
        }
      ],
      "providerMetadata": {
        "s3TemplateURL": "https://s3.amazonaws.com/amplify-cherrye-dev-113949-deployment/amplify-cfn-templates/api/cherryeAPI-cloudformation-template.json",
        "logicalId": "apicherryeAPI"
      },
      "lastPushTimeStamp": "2021-04-30T05:32:02.603Z",
      "output": {
        "ApiName": "cherryeAPI",
        "RootUrl": "https://z7sczm14te.execute-api.us-west-2.amazonaws.com/dev",
        "ApiId": "z7sczm14te"
      },
      "lastPushDirHash": "yXsjF4+aWbHg3diGsEPYBbdW0ME="
    },
    "cherryeAPICart": {
      "service": "API Gateway",
      "providerPlugin": "awscloudformation",
      "dependsOn": [
        {
          "category": "function",
          "resourceName": "handlecartitemsFunction",
          "attributes": [
            "Name",
            "Arn"
          ]
        }
      ],
      "providerMetadata": {
        "s3TemplateURL": "https://s3.amazonaws.com/amplify-cherrye-dev-113949-deployment/amplify-cfn-templates/api/cherryeAPICart-cloudformation-template.json",
        "logicalId": "apicherryeAPICart"
      },
      "lastPushTimeStamp": "2021-04-30T05:32:02.626Z",
      "output": {
        "ApiName": "cherryeAPICart",
        "RootUrl": "https://teokhzk555.execute-api.us-west-2.amazonaws.com/dev",
        "ApiId": "teokhzk555"
      },
      "lastPushDirHash": "PsO5i4llsijHvSbwob20KSHPWuc="
    }
  }
}